vcoutils/__init__.py
vcoutils/extrachecks.py
vcoutils/genid.py
vcoutils/intents.py
vcoutils/leakybucket.py
vcoutils-4.3.1.dist-info/LICENSE
vcoutils-4.3.1.dist-info/METADATA
vcoutils-4.3.1.dist-info/WHEEL
vcoutils-4.3.1.dist-info/top_level.txt
vcoutils-4.3.1.dist-info/RECORD
