Metadata-Version: 2.1
Name: vcoutils
Version: 4.3.1
Summary: A collection of utlities I have made or adapted for convenience.
Home-page: https://github.com/vcokltfre/vcoutils
Author: vcokltfre
Author-email: vcokltfre@gmail.com
License: UNKNOWN
Platform: UNKNOWN
